LLMeta/__init__.py
LLMeta/formated_output.py
LLMeta/generate_hypothetical_text.py
LLMeta/generate_judgement.py
LLMeta/get_relate_doc.py
LLMeta/markdown_to_vectorstore.py
LLMeta/process_row.py
LLMeta/process_threads.py
LLMeta/save_vectorstore.py
LLMeta/setup.py
LLMeta/split_markdown_file.py
LLMeta-1.0.0.dist-info/LICENSE
LLMeta-1.0.0.dist-info/METADATA
LLMeta-1.0.0.dist-info/WHEEL
LLMeta-1.0.0.dist-info/top_level.txt
LLMeta-1.0.0.dist-info/RECORD
